mosaic/__init__.py
mosaic/cloud.py
mosaic/local.py
mosaic/mosaic.py
mosaic/schemas.py
mosaic/utils.py
mosaic_mmrag-0.2.3.dist-info/licenses/LICENSE
mosaic_mmrag-0.2.3.dist-info/METADATA
mosaic_mmrag-0.2.3.dist-info/WHEEL
mosaic_mmrag-0.2.3.dist-info/top_level.txt
mosaic_mmrag-0.2.3.dist-info/RECORD
