Metadata-Version: 2.4
Name: mosaic-mmrag
Version: 0.2.3
Summary: Use late-interaction multi-modal models such as ColPali & ColQwen2 for retrieval, with Qdrant as a backend.
Author-email: Abdullah Meda <abdullah.meda@gmail.com>
License: 
Project-URL: Homepage, https://github.com/abdullahmeda/mosaic
Project-URL: Bug Tracker, https://github.com/abdullahmeda/mosaic/issues
Classifier: Programming Language :: Python :: 3
Classifier: License :: OSI Approved :: Apache Software License
Classifier: Operating System :: OS Independent
Requires-Python: >=3.9
License-File: LICENSE
Requires-Dist: pdf2image
Requires-Dist: qdrant-client>=1.13.3
Requires-Dist: gotenberg-client>=0.10.0
Provides-Extra: dev
Requires-Dist: pytest>=7.4.0; extra == "dev"
Requires-Dist: ruff>=0.1.9; extra == "dev"
Provides-Extra: server
Requires-Dist: uvicorn; extra == "server"
Requires-Dist: fastapi; extra == "server"
Provides-Extra: local
Requires-Dist: colpali_engine>=0.3.8; extra == "local"
Dynamic: license-file
